drb_impl_era5/__init__.py
drb_impl_era5/_version.py
drb_impl_era5/cortex.yml
drb_impl_era5/era5_constants.py
drb_impl_era5/era5_nodes.py
drb_impl_era5/era5_predicates.py
drb_impl_era5/exceptions.py
drb_impl_era5/factory.py
drb_impl_era5-1.0.1.data/data/requirements.txt
drb_impl_era5-1.0.1.dist-info/METADATA
drb_impl_era5-1.0.1.dist-info/WHEEL
drb_impl_era5-1.0.1.dist-info/entry_points.txt
drb_impl_era5-1.0.1.dist-info/top_level.txt
drb_impl_era5-1.0.1.dist-info/RECORD
