Metadata-Version: 2.1
Name: drb-impl-era5
Version: 1.0.1
Summary: DRB era5 OGC Service implementation
Home-page: https://gitlab.com/drb-python/impl/era5
Author: GAEL Systems
Author-email: drb-python@gael.fr
License: UNKNOWN
Platform: UNKNOWN
Classifier: Programming Language :: Python :: 3.8
Classifier: License :: OSI Approved :: Apache Software License
Classifier: Operating System :: OS Independent
Requires-Python: >=3.8
Requires-Dist: drb (<1.1.0,>=1.0.1)
Requires-Dist: drb-impl-http (<1.1.0,>=1.0.8)
Requires-Dist: drb-impl-netcdf (<1.1.0,>=1.0.1)
Requires-Dist: cdsapi (==0.5.1)
Requires-Dist: requests (~=2.27.1)
